LICENSE
README.md
setup.py
gengli/__init__.py
gengli/glitch_generator.py
gengli/utils.py
gengli.egg-info/PKG-INFO
gengli.egg-info/SOURCES.txt
gengli.egg-info/dependency_links.txt
gengli.egg-info/requires.txt
gengli.egg-info/top_level.txt
gengli/ctgan/__init__.py
gengli/ctgan/model.py
gengli/ctgan/train.py
gengli/ctgan/weights/blip_H1_CTGAN_state_G.pth
gengli/ctgan/weights/blip_L1_CTGAN_state_G.pth