Metadata-Version: 2.1
Name: gengli
Version: 0.0.1
Summary: Glitch generation with Generative Adversarial Network
Home-page: https://git.ligo.org/melissa.lopez/gengli
Author: Melissa Lopez
Author-email: m.lopez@uu.nl
Maintainer: Stefano Schmidt
Maintainer-email: s.schmidt@uu.nl
License: GNU GENERAL PUBLIC LICENSE v3
Platform: UNKNOWN
Classifier: Programming Language :: Python :: 3
Classifier: Operating System :: OS Independent
Requires-Python: >=3.7
License-File: LICENSE
